bgAna/__init__.py
bgAna/main.py
bgAna-0.0.0.dist-info/LICENSE
bgAna-0.0.0.dist-info/METADATA
bgAna-0.0.0.dist-info/WHEEL
bgAna-0.0.0.dist-info/entry_points.txt
bgAna-0.0.0.dist-info/top_level.txt
bgAna-0.0.0.dist-info/RECORD
