Metadata-Version: 2.1
Name: bgAna
Version: 0.0.0
Summary: Background Analyzer. Heuristics to get the background color of any image.
Home-page: https://github.com/Madoshakalaka/bgAna
Author: Matt Yan
Author-email: syan4@ualberta.ca
License: UNKNOWN
Project-URL: Bug Reports, https://github.com/Madoshakalaka/bgAna/issues
Project-URL: Funding, https://github.com/Madoshakalaka/bgAna
Project-URL: Say Thanks!, https://github.com/Madoshakalaka/bgAna
Project-URL: Source, https://github.com/Madoshakalaka/bgAna
Keywords: computer vision
Platform: UNKNOWN
Classifier: Development Status :: 3 - Alpha
Classifier: Intended Audience :: Developers
Classifier: Topic :: Software Development :: Build Tools
Classifier: License :: OSI Approved :: MIT License
Classifier: Programming Language :: Python :: 3.5
Classifier: Programming Language :: Python :: 3.6
Classifier: Programming Language :: Python :: 3.7
Requires-Python: >=3.5
Requires-Dist: numpy
Requires-Dist: opencv-python
Requires-Dist: scipy
